ezmm/__init__.py
ezmm/embedding.py
ezmm/util.py
ezmm/common/__init__.py
ezmm/common/multimodal_sequence.py
ezmm/common/registry.py
ezmm/common/items/__init__.py
ezmm/common/items/audio.py
ezmm/common/items/image.py
ezmm/common/items/item.py
ezmm/common/items/video.py
ezmm/ui/__init__.py
ezmm/ui/common.py
ezmm/ui/main.py
ezmm-0.5.0.dist-info/licenses/LICENSE
ezmm-0.5.0.dist-info/METADATA
ezmm-0.5.0.dist-info/WHEEL
ezmm-0.5.0.dist-info/top_level.txt
ezmm-0.5.0.dist-info/RECORD
