Metadata-Version: 2.4
Name: ezMM
Version: 0.5.0
Summary: Lightweight Python kit for easy multimodal data processing.
Author-email: Mark Rothermel <mark.rothermel@tu-darmstadt.de>
License-Expression: Apache-2.0
Project-URL: Homepage, https://github.com/multimodal-ai-lab/ezmm
Project-URL: Issues, https://github.com/multimodal-ai-lab/ezmm/issues
Requires-Python: >=3.11
License-File: LICENSE
Requires-Dist: pillow
Requires-Dist: pillow-avif-plugin
Requires-Dist: opencv-python
Requires-Dist: uvicorn
Requires-Dist: fastapi
Requires-Dist: starlette
Requires-Dist: markdown
Requires-Dist: imageio-ffmpeg
Requires-Dist: m3u8
Requires-Dist: jinja2
Requires-Dist: fastembed
Dynamic: license-file
